simple_ddl_parser/__init__.py
simple_ddl_parser/cli.py
simple_ddl_parser/ddl_parser.py
simple_ddl_parser/dialects/__init__.py
simple_ddl_parser/dialects/athena.py
simple_ddl_parser/dialects/bigquery.py
simple_ddl_parser/dialects/hql.py
simple_ddl_parser/dialects/ibm.py
simple_ddl_parser/dialects/mssql.py
simple_ddl_parser/dialects/mysql.py
simple_ddl_parser/dialects/oracle.py
simple_ddl_parser/dialects/psql.py
simple_ddl_parser/dialects/redshift.py
simple_ddl_parser/dialects/snowflake.py
simple_ddl_parser/dialects/spark_sql.py
simple_ddl_parser/dialects/sql.py
simple_ddl_parser/exception.py
simple_ddl_parser/output/base_data.py
simple_ddl_parser/output/core.py
simple_ddl_parser/output/custom_schemas.py
simple_ddl_parser/output/dialects.py
simple_ddl_parser/output/table_data.py
simple_ddl_parser/parser.py
simple_ddl_parser/parsetab.py
simple_ddl_parser/tokens.py
simple_ddl_parser/utils.py
simple_ddl_parser-1.10.0.dist-info/METADATA
simple_ddl_parser-1.10.0.dist-info/WHEEL
simple_ddl_parser-1.10.0.dist-info/entry_points.txt
simple_ddl_parser-1.10.0.dist-info/licenses/LICENSE
simple_ddl_parser-1.10.0.dist-info/RECORD
