Metadata-Version: 2.4
Name: simple-ddl-parser
Version: 1.10.0
Summary: Simple DDL Parser to parse SQL & dialects like HQL, TSQL (MSSQL), Oracle, AWS Redshift, Snowflake, MySQL, PostgreSQL, etc ddl files to json/python dict with full information about columns: types, defaults, primary keys, etc.; sequences, alters, custom types & other entities from ddl.
License: MIT
License-File: LICENSE
Author: Iuliia Volkova
Author-email: xnuinside@gmail.com
Requires-Python: >=3.9,<4.0
Classifier: License :: OSI Approved :: MIT License
Classifier: Programming Language :: PL/SQL
Classifier: Programming Language :: Python :: 3
Classifier: Programming Language :: Python :: 3.9
Classifier: Programming Language :: Python :: 3.10
Classifier: Programming Language :: Python :: 3.11
Classifier: Programming Language :: Python :: 3.12
Classifier: Programming Language :: Python :: 3.13
Classifier: Programming Language :: Python :: 3.14
Classifier: Programming Language :: SQL
Classifier: Topic :: Software Development
Classifier: Topic :: Software Development :: Libraries
Classifier: Topic :: Software Development :: Libraries :: Python Modules
Classifier: Topic :: Utilities
Requires-Dist: ply (>=3.11,<4.0)
Project-URL: Homepage, https://github.com/xnuinside/simple-ddl-parser
Project-URL: Repository, https://github.com/xnuinside/simple-ddl-parser
